[
	{
		"title": "神活泼有功效的道 20161001",
		"path": "http://media.febcchinese.org/streaming/mw/mw161001.mp3",
		"duration": 1760,
		"size": "14.1M",
		"albumName": "旷野吗哪 2016年冬季合集",
		"id": 6216000001,
		"albumId": 6216,
		"albumtitle": "旷野吗哪 2016年冬季合集(1)",
		"textContent": ""
	},
	{
		"title": "喜乐的人生 20161002",
		"path": "http://media.febcchinese.org/streaming/mw/mw161002.mp3",
		"duration": 1760,
		"size": "14.1M",
		"albumName": "旷野吗哪 2016年冬季合集",
		"id": 6216000002,
		"albumId": 6216,
		"albumtitle": "旷野吗哪 2016年冬季合集(2)",
		"textContent": ""
	},
	{
		"title": "金色的黎明 20161003",
		"path": "http://media.febcchinese.org/streaming/mw/mw161003.mp3",
		"duration": 1760,
		"size": "14.1M",
		"albumName": "旷野吗哪 2016年冬季合集",
		"id": 6216000003,
		"albumId": 6216,
		"albumtitle": "旷野吗哪 2016年冬季合集(3)",
		"textContent": ""
	},
	{
		"title": "主是好牧人 20161004",
		"path": "http://media.febcchinese.org/streaming/mw/mw161004.mp3",
		"duration": 1760,
		"size": "14.1M",
		"albumName": "旷野吗哪 2016年冬季合集",
		"id": 6216000004,
		"albumId": 6216,
		"albumtitle": "旷野吗哪 2016年冬季合集(4)",
		"textContent": ""
	},
	{
		"title": "落单的麻雀 20161005",
		"path": "http://media.febcchinese.org/streaming/mw/mw161005.mp3",
		"duration": 1760,
		"size": "14.1M",
		"albumName": "旷野吗哪 2016年冬季合集",
		"id": 6216000005,
		"albumId": 6216,
		"albumtitle": "旷野吗哪 2016年冬季合集(5)",
		"textContent": ""
	},
	{
		"title": "搬迁到天上 20161006",
		"path": "http://media.febcchinese.org/streaming/mw/mw161006.mp3",
		"duration": 1760,
		"size": "14.1M",
		"albumName": "旷野吗哪 2016年冬季合集",
		"id": 6216000006,
		"albumId": 6216,
		"albumtitle": "旷野吗哪 2016年冬季合集(6)",
		"textContent": ""
	},
	{
		"title": "老人的祷告 20161007",
		"path": "http://media.febcchinese.org/streaming/mw/mw161007.mp3",
		"duration": 1760,
		"size": "14.1M",
		"albumName": "旷野吗哪 2016年冬季合集",
		"id": 6216000007,
		"albumId": 6216,
		"albumtitle": "旷野吗哪 2016年冬季合集(7)",
		"textContent": ""
	},
	{
		"title": "足能得胜 20161008",
		"path": "http://media.febcchinese.org/streaming/mw/mw161008.mp3",
		"duration": 1760,
		"size": "14.1M",
		"albumName": "旷野吗哪 2016年冬季合集",
		"id": 6216000008,
		"albumId": 6216,
		"albumtitle": "旷野吗哪 2016年冬季合集(8)",
		"textContent": ""
	},
	{
		"title": "一次只要过一日 20161009",
		"path": "http://media.febcchinese.org/streaming/mw/mw161009.mp3",
		"duration": 1760,
		"size": "14.1M",
		"albumName": "旷野吗哪 2016年冬季合集",
		"id": 6216000009,
		"albumId": 6216,
		"albumtitle": "旷野吗哪 2016年冬季合集(9)",
		"textContent": ""
	},
	{
		"title": "大胆运用 20161010",
		"path": "http://media.febcchinese.org/streaming/mw/mw161010.mp3",
		"duration": 1760,
		"size": "14.1M",
		"albumName": "旷野吗哪 2016年冬季合集",
		"id": 6216000010,
		"albumId": 6216,
		"albumtitle": "旷野吗哪 2016年冬季合集(10)",
		"textContent": ""
	},
	{
		"title": "美丽天城 20161011",
		"path": "http://media.febcchinese.org/streaming/mw/mw161011.mp3",
		"duration": 1760,
		"size": "14.1M",
		"albumName": "旷野吗哪 2016年冬季合集",
		"id": 6216000011,
		"albumId": 6216,
		"albumtitle": "旷野吗哪 2016年冬季合集(11)",
		"textContent": ""
	},
	{
		"title": "困难中的盼望 20161012",
		"path": "http://media.febcchinese.org/streaming/mw/mw161012.mp3",
		"duration": 1760,
		"size": "14.1M",
		"albumName": "旷野吗哪 2016年冬季合集",
		"id": 6216000012,
		"albumId": 6216,
		"albumtitle": "旷野吗哪 2016年冬季合集(12)",
		"textContent": ""
	},
	{
		"title": "破茧而出 20161013",
		"path": "http://media.febcchinese.org/streaming/mw/mw161013.mp3",
		"duration": 1760,
		"size": "14.1M",
		"albumName": "旷野吗哪 2016年冬季合集",
		"id": 6216000013,
		"albumId": 6216,
		"albumtitle": "旷野吗哪 2016年冬季合集(13)",
		"textContent": ""
	},
	{
		"title": "无须忍受老年 20161014",
		"path": "http://media.febcchinese.org/streaming/mw/mw161014.mp3",
		"duration": 1760,
		"size": "14.1M",
		"albumName": "旷野吗哪 2016年冬季合集",
		"id": 6216000014,
		"albumId": 6216,
		"albumtitle": "旷野吗哪 2016年冬季合集(14)",
		"textContent": ""
	},
	{
		"title": "探险心态 20161015",
		"path": "http://media.febcchinese.org/streaming/mw/mw161015.mp3",
		"duration": 1760,
		"size": "14.1M",
		"albumName": "旷野吗哪 2016年冬季合集",
		"id": 6216000015,
		"albumId": 6216,
		"albumtitle": "旷野吗哪 2016年冬季合集(15)",
		"textContent": ""
	},
	{
		"title": "全力以赴 20161016",
		"path": "http://media.febcchinese.org/streaming/mw/mw161016.mp3",
		"duration": 1760,
		"size": "14.1M",
		"albumName": "旷野吗哪 2016年冬季合集",
		"id": 6216000016,
		"albumId": 6216,
		"albumtitle": "旷野吗哪 2016年冬季合集(16)",
		"textContent": ""
	},
	{
		"title": "就是这么真实 20161017",
		"path": "http://media.febcchinese.org/streaming/mw/mw161017.mp3",
		"duration": 1760,
		"size": "14.1M",
		"albumName": "旷野吗哪 2016年冬季合集",
		"id": 6216000017,
		"albumId": 6216,
		"albumtitle": "旷野吗哪 2016年冬季合集(17)",
		"textContent": ""
	},
	{
		"title": "清晨的祷愿 20161018",
		"path": "http://media.febcchinese.org/streaming/mw/mw161018.mp3",
		"duration": 1760,
		"size": "14.1M",
		"albumName": "旷野吗哪 2016年冬季合集",
		"id": 6216000018,
		"albumId": 6216,
		"albumtitle": "旷野吗哪 2016年冬季合集(18)",
		"textContent": ""
	},
	{
		"title": "祷告良辰 20161019",
		"path": "http://media.febcchinese.org/streaming/mw/mw161019.mp3",
		"duration": 1760,
		"size": "14.1M",
		"albumName": "旷野吗哪 2016年冬季合集",
		"id": 6216000019,
		"albumId": 6216,
		"albumtitle": "旷野吗哪 2016年冬季合集(19)",
		"textContent": ""
	},
	{
		"title": "唱出喜乐和感恩 20161020",
		"path": "http://media.febcchinese.org/streaming/mw/mw161020.mp3",
		"duration": 1760,
		"size": "14.1M",
		"albumName": "旷野吗哪 2016年冬季合集",
		"id": 6216000020,
		"albumId": 6216,
		"albumtitle": "旷野吗哪 2016年冬季合集(20)",
		"textContent": ""
	},
	{
		"title": "勇于面对死亡 20161021",
		"path": "http://media.febcchinese.org/streaming/mw/mw161021.mp3",
		"duration": 1760,
		"size": "14.1M",
		"albumName": "旷野吗哪 2016年冬季合集",
		"id": 6216000021,
		"albumId": 6216,
		"albumtitle": "旷野吗哪 2016年冬季合集(21)",
		"textContent": ""
	},
	{
		"title": "老干新枝 20161022",
		"path": "http://media.febcchinese.org/streaming/mw/mw161022.mp3",
		"duration": 1760,
		"size": "14.1M",
		"albumName": "旷野吗哪 2016年冬季合集",
		"id": 6216000022,
		"albumId": 6216,
		"albumtitle": "旷野吗哪 2016年冬季合集(22)",
		"textContent": ""
	},
	{
		"title": "我必不怕遭害 20161023",
		"path": "http://media.febcchinese.org/streaming/mw/mw161023.mp3",
		"duration": 1760,
		"size": "14.1M",
		"albumName": "旷野吗哪 2016年冬季合集",
		"id": 6216000023,
		"albumId": 6216,
		"albumtitle": "旷野吗哪 2016年冬季合集(23)",
		"textContent": ""
	},
	{
		"title": "活得长又活得好 20161024",
		"path": "http://media.febcchinese.org/streaming/mw/mw161024.mp3",
		"duration": 1760,
		"size": "14.1M",
		"albumName": "旷野吗哪 2016年冬季合集",
		"id": 6216000024,
		"albumId": 6216,
		"albumtitle": "旷野吗哪 2016年冬季合集(24)",
		"textContent": ""
	},
	{
		"title": "完全的祝福 20161025",
		"path": "http://media.febcchinese.org/streaming/mw/mw161025.mp3",
		"duration": 1760,
		"size": "14.1M",
		"albumName": "旷野吗哪 2016年冬季合集",
		"id": 6216000025,
		"albumId": 6216,
		"albumtitle": "旷野吗哪 2016年冬季合集(25)",
		"textContent": ""
	},
	{
		"title": "保持你的直觉与判断力 20161026",
		"path": "http://media.febcchinese.org/streaming/mw/mw161026.mp3",
		"duration": 1760,
		"size": "14.1M",
		"albumName": "旷野吗哪 2016年冬季合集",
		"id": 6216000026,
		"albumId": 6216,
		"albumtitle": "旷野吗哪 2016年冬季合集(26)",
		"textContent": ""
	},
	{
		"title": "靠主胸前 20161027",
		"path": "http://media.febcchinese.org/streaming/mw/mw161027.mp3",
		"duration": 1760,
		"size": "14.1M",
		"albumName": "旷野吗哪 2016年冬季合集",
		"id": 6216000027,
		"albumId": 6216,
		"albumtitle": "旷野吗哪 2016年冬季合集(27)",
		"textContent": ""
	},
	{
		"title": "摒弃自我中心的习性 20161028",
		"path": "http://media.febcchinese.org/streaming/mw/mw161028.mp3",
		"duration": 1760,
		"size": "14.1M",
		"albumName": "旷野吗哪 2016年冬季合集",
		"id": 6216000028,
		"albumId": 6216,
		"albumtitle": "旷野吗哪 2016年冬季合集(28)",
		"textContent": ""
	},
	{
		"title": "效法基督的舍己 20161029",
		"path": "http://media.febcchinese.org/streaming/mw/mw161029.mp3",
		"duration": 1760,
		"size": "14.1M",
		"albumName": "旷野吗哪 2016年冬季合集",
		"id": 6216000029,
		"albumId": 6216,
		"albumtitle": "旷野吗哪 2016年冬季合集(29)",
		"textContent": ""
	},
	{
		"title": "与神同工 20161030",
		"path": "http://media.febcchinese.org/streaming/mw/mw161030.mp3",
		"duration": 1760,
		"size": "14.1M",
		"albumName": "旷野吗哪 2016年冬季合集",
		"id": 6216000030,
		"albumId": 6216,
		"albumtitle": "旷野吗哪 2016年冬季合集(30)",
		"textContent": ""
	},
	{
		"title": "传道 20161031",
		"path": "http://media.febcchinese.org/streaming/mw/mw161031.mp3",
		"duration": 1760,
		"size": "14.1M",
		"albumName": "旷野吗哪 2016年冬季合集",
		"id": 6216000031,
		"albumId": 6216,
		"albumtitle": "旷野吗哪 2016年冬季合集(31)",
		"textContent": ""
	},
	{
		"title": "清醒时刻 20161101",
		"path": "http://media.febcchinese.org/streaming/mw/mw161101.mp3",
		"duration": 1760,
		"size": "14.1M",
		"albumName": "旷野吗哪 2016年冬季合集",
		"id": 6216000032,
		"albumId": 6216,
		"albumtitle": "旷野吗哪 2016年冬季合集(32)",
		"textContent": ""
	},
	{
		"title": "我是否忠诚？ 20161102",
		"path": "http://media.febcchinese.org/streaming/mw/mw161102.mp3",
		"duration": 1760,
		"size": "14.1M",
		"albumName": "旷野吗哪 2016年冬季合集",
		"id": 6216000033,
		"albumId": 6216,
		"albumtitle": "旷野吗哪 2016年冬季合集(33)",
		"textContent": ""
	},
	{
		"title": "想念主爱 20161103",
		"path": "http://media.febcchinese.org/streaming/mw/mw161103.mp3",
		"duration": 1760,
		"size": "14.1M",
		"albumName": "旷野吗哪 2016年冬季合集",
		"id": 6216000034,
		"albumId": 6216,
		"albumtitle": "旷野吗哪 2016年冬季合集(34)",
		"textContent": ""
	},
	{
		"title": "讨主喜悦/ 20161104",
		"path": "http://media.febcchinese.org/streaming/mw/mw161104.mp3",
		"duration": 1760,
		"size": "14.1M",
		"albumName": "旷野吗哪 2016年冬季合集",
		"id": 6216000035,
		"albumId": 6216,
		"albumtitle": "旷野吗哪 2016年冬季合集(35)",
		"textContent": ""
	},
	{
		"title": "图案在背面 20161105",
		"path": "http://media.febcchinese.org/streaming/mw/mw161105.mp3",
		"duration": 1760,
		"size": "14.1M",
		"albumName": "旷野吗哪 2016年冬季合集",
		"id": 6216000036,
		"albumId": 6216,
		"albumtitle": "旷野吗哪 2016年冬季合集(36)",
		"textContent": ""
	},
	{
		"title": "一心不能二用 20161106",
		"path": "http://media.febcchinese.org/streaming/mw/mw161106.mp3",
		"duration": 1760,
		"size": "14.1M",
		"albumName": "旷野吗哪 2016年冬季合集",
		"id": 6216000037,
		"albumId": 6216,
		"albumtitle": "旷野吗哪 2016年冬季合集(37)",
		"textContent": ""
	},
	{
		"title": "宽容的气度 20161107",
		"path": "http://media.febcchinese.org/streaming/mw/mw161107.mp3",
		"duration": 1760,
		"size": "14.1M",
		"albumName": "旷野吗哪 2016年冬季合集",
		"id": 6216000038,
		"albumId": 6216,
		"albumtitle": "旷野吗哪 2016年冬季合集(38)",
		"textContent": ""
	},
	{
		"title": "过高尚的生活 20161108",
		"path": "http://media.febcchinese.org/streaming/mw/mw161108.mp3",
		"duration": 1760,
		"size": "14.1M",
		"albumName": "旷野吗哪 2016年冬季合集",
		"id": 6216000039,
		"albumId": 6216,
		"albumtitle": "旷野吗哪 2016年冬季合集(39)",
		"textContent": ""
	},
	{
		"title": "荣耀的释放 20161109",
		"path": "http://media.febcchinese.org/streaming/mw/mw161109.mp3",
		"duration": 1760,
		"size": "14.1M",
		"albumName": "旷野吗哪 2016年冬季合集",
		"id": 6216000040,
		"albumId": 6216,
		"albumtitle": "旷野吗哪 2016年冬季合集(40)",
		"textContent": ""
	},
	{
		"title": "实在是我 20161110",
		"path": "http://media.febcchinese.org/streaming/mw/mw161110.mp3",
		"duration": 1760,
		"size": "14.1M",
		"albumName": "旷野吗哪 2016年冬季合集",
		"id": 6216000041,
		"albumId": 6216,
		"albumtitle": "旷野吗哪 2016年冬季合集(41)",
		"textContent": ""
	},
	{
		"title": "在神没有难成就的事 20161111",
		"path": "http://media.febcchinese.org/streaming/mw/mw161111.mp3",
		"duration": 1760,
		"size": "14.1M",
		"albumName": "旷野吗哪 2016年冬季合集",
		"id": 6216000042,
		"albumId": 6216,
		"albumtitle": "旷野吗哪 2016年冬季合集(42)",
		"textContent": ""
	},
	{
		"title": "至高者的隐密处 20161112",
		"path": "http://media.febcchinese.org/streaming/mw/mw161112.mp3",
		"duration": 1760,
		"size": "14.1M",
		"albumName": "旷野吗哪 2016年冬季合集",
		"id": 6216000043,
		"albumId": 6216,
		"albumtitle": "旷野吗哪 2016年冬季合集(43)",
		"textContent": ""
	},
	{
		"title": "常作祂所喜悦的事 20161113",
		"path": "http://media.febcchinese.org/streaming/mw/mw161113.mp3",
		"duration": 1760,
		"size": "14.1M",
		"albumName": "旷野吗哪 2016年冬季合集",
		"id": 6216000044,
		"albumId": 6216,
		"albumtitle": "旷野吗哪 2016年冬季合集(44)",
		"textContent": ""
	},
	{
		"title": "为王作工 20161114",
		"path": "http://media.febcchinese.org/streaming/mw/mw161114.mp3",
		"duration": 1760,
		"size": "14.1M",
		"albumName": "旷野吗哪 2016年冬季合集",
		"id": 6216000045,
		"albumId": 6216,
		"albumtitle": "旷野吗哪 2016年冬季合集(45)",
		"textContent": ""
	},
	{
		"title": "做你自己 20161115",
		"path": "http://media.febcchinese.org/streaming/mw/mw161115.mp3",
		"duration": 1760,
		"size": "14.1M",
		"albumName": "旷野吗哪 2016年冬季合集",
		"id": 6216000046,
		"albumId": 6216,
		"albumtitle": "旷野吗哪 2016年冬季合集(46)",
		"textContent": ""
	},
	{
		"title": "洁净行为 20161116",
		"path": "http://media.febcchinese.org/streaming/mw/mw161116.mp3",
		"duration": 1760,
		"size": "14.1M",
		"albumName": "旷野吗哪 2016年冬季合集",
		"id": 6216000047,
		"albumId": 6216,
		"albumtitle": "旷野吗哪 2016年冬季合集(47)",
		"textContent": ""
	},
	{
		"title": "尽力救人 20161117",
		"path": "http://media.febcchinese.org/streaming/mw/mw161117.mp3",
		"duration": 1760,
		"size": "14.1M",
		"albumName": "旷野吗哪 2016年冬季合集",
		"id": 6216000048,
		"albumId": 6216,
		"albumtitle": "旷野吗哪 2016年冬季合集(48)",
		"textContent": ""
	},
	{
		"title": "献上最美 20161118",
		"path": "http://media.febcchinese.org/streaming/mw/mw161118.mp3",
		"duration": 1760,
		"size": "14.1M",
		"albumName": "旷野吗哪 2016年冬季合集",
		"id": 6216000049,
		"albumId": 6216,
		"albumtitle": "旷野吗哪 2016年冬季合集(49)",
		"textContent": ""
	},
	{
		"title": "了解代替批评 20161119",
		"path": "http://media.febcchinese.org/streaming/mw/mw161119.mp3",
		"duration": 1760,
		"size": "14.1M",
		"albumName": "旷野吗哪 2016年冬季合集",
		"id": 6216000050,
		"albumId": 6216,
		"albumtitle": "旷野吗哪 2016年冬季合集(50)",
		"textContent": ""
	},
	{
		"title": "尽你所能的祷告 20161120",
		"path": "http://media.febcchinese.org/streaming/mw/mw161120.mp3",
		"duration": 1760,
		"size": "14.1M",
		"albumName": "旷野吗哪 2016年冬季合集",
		"id": 6216000051,
		"albumId": 6216,
		"albumtitle": "旷野吗哪 2016年冬季合集(51)",
		"textContent": ""
	},
	{
		"title": "立刻行动 20161121",
		"path": "http://media.febcchinese.org/streaming/mw/mw161121.mp3",
		"duration": 1760,
		"size": "14.1M",
		"albumName": "旷野吗哪 2016年冬季合集",
		"id": 6216000052,
		"albumId": 6216,
		"albumtitle": "旷野吗哪 2016年冬季合集(52)",
		"textContent": ""
	},
	{
		"title": "冠冕或十字架 20161122",
		"path": "http://media.febcchinese.org/streaming/mw/mw161122.mp3",
		"duration": 1760,
		"size": "14.1M",
		"albumName": "旷野吗哪 2016年冬季合集",
		"id": 6216000053,
		"albumId": 6216,
		"albumtitle": "旷野吗哪 2016年冬季合集(53)",
		"textContent": ""
	},
	{
		"title": "专心爱主 20161123",
		"path": "http://media.febcchinese.org/streaming/mw/mw161123.mp3",
		"duration": 1760,
		"size": "14.1M",
		"albumName": "旷野吗哪 2016年冬季合集",
		"id": 6216000054,
		"albumId": 6216,
		"albumtitle": "旷野吗哪 2016年冬季合集(54)",
		"textContent": ""
	},
	{
		"title": "神所指示的地方 20161124",
		"path": "http://media.febcchinese.org/streaming/mw/mw161124.mp3",
		"duration": 1760,
		"size": "14.1M",
		"albumName": "旷野吗哪 2016年冬季合集",
		"id": 6216000055,
		"albumId": 6216,
		"albumtitle": "旷野吗哪 2016年冬季合集(55)",
		"textContent": ""
	},
	{
		"title": "祂能拯救到底 20161125",
		"path": "http://media.febcchinese.org/streaming/mw/mw161125.mp3",
		"duration": 1760,
		"size": "14.1M",
		"albumName": "旷野吗哪 2016年冬季合集",
		"id": 6216000056,
		"albumId": 6216,
		"albumtitle": "旷野吗哪 2016年冬季合集(56)",
		"textContent": ""
	},
	{
		"title": "安静的时刻 20161126",
		"path": "http://media.febcchinese.org/streaming/mw/mw161126.mp3",
		"duration": 1760,
		"size": "14.1M",
		"albumName": "旷野吗哪 2016年冬季合集",
		"id": 6216000057,
		"albumId": 6216,
		"albumtitle": "旷野吗哪 2016年冬季合集(57)",
		"textContent": ""
	},
	{
		"title": "最荣誉的头衔 20161127",
		"path": "http://media.febcchinese.org/streaming/mw/mw161127.mp3",
		"duration": 1760,
		"size": "14.1M",
		"albumName": "旷野吗哪 2016年冬季合集",
		"id": 6216000058,
		"albumId": 6216,
		"albumtitle": "旷野吗哪 2016年冬季合集(58)",
		"textContent": ""
	},
	{
		"title": "慎选配偶 20161128",
		"path": "http://media.febcchinese.org/streaming/mw/mw161128.mp3",
		"duration": 1760,
		"size": "14.1M",
		"albumName": "旷野吗哪 2016年冬季合集",
		"id": 6216000059,
		"albumId": 6216,
		"albumtitle": "旷野吗哪 2016年冬季合集(59)",
		"textContent": ""
	},
	{
		"title": "饶恕并祝福 20161129",
		"path": "http://media.febcchinese.org/streaming/mw/mw161129.mp3",
		"duration": 1760,
		"size": "14.1M",
		"albumName": "旷野吗哪 2016年冬季合集",
		"id": 6216000060,
		"albumId": 6216,
		"albumtitle": "旷野吗哪 2016年冬季合集(60)",
		"textContent": ""
	},
	{
		"title": "儆醒小罪 20161130",
		"path": "http://media.febcchinese.org/streaming/mw/mw161130.mp3",
		"duration": 1760,
		"size": "14.1M",
		"albumName": "旷野吗哪 2016年冬季合集",
		"id": 6216000061,
		"albumId": 6216,
		"albumtitle": "旷野吗哪 2016年冬季合集(61)",
		"textContent": ""
	},
	{
		"title": "仅此一生 20161201",
		"path": "http://media.febcchinese.org/streaming/mw/mw161201.mp3",
		"duration": 1760,
		"size": "14.1M",
		"albumName": "旷野吗哪 2016年冬季合集",
		"id": 6216000062,
		"albumId": 6216,
		"albumtitle": "旷野吗哪 2016年冬季合集(62)",
		"textContent": ""
	},
	{
		"title": "施比受更为有福 20161202",
		"path": "http://media.febcchinese.org/streaming/mw/mw161202.mp3",
		"duration": 1760,
		"size": "14.1M",
		"albumName": "旷野吗哪 2016年冬季合集",
		"id": 6216000063,
		"albumId": 6216,
		"albumtitle": "旷野吗哪 2016年冬季合集(63)",
		"textContent": ""
	},
	{
		"title": "开我眼睛使我看见 20161203",
		"path": "http://media.febcchinese.org/streaming/mw/mw161203.mp3",
		"duration": 1760,
		"size": "14.1M",
		"albumName": "旷野吗哪 2016年冬季合集",
		"id": 6216000064,
		"albumId": 6216,
		"albumtitle": "旷野吗哪 2016年冬季合集(64)",
		"textContent": ""
	},
	{
		"title": "奇妙的爱 20161204",
		"path": "http://media.febcchinese.org/streaming/mw/mw161204.mp3",
		"duration": 1760,
		"size": "14.1M",
		"albumName": "旷野吗哪 2016年冬季合集",
		"id": 6216000065,
		"albumId": 6216,
		"albumtitle": "旷野吗哪 2016年冬季合集(65)",
		"textContent": ""
	},
	{
		"title": "奇哉主道 20161205",
		"path": "http://media.febcchinese.org/streaming/mw/mw161205.mp3",
		"duration": 1760,
		"size": "14.1M",
		"albumName": "旷野吗哪 2016年冬季合集",
		"id": 6216000066,
		"albumId": 6216,
		"albumtitle": "旷野吗哪 2016年冬季合集(66)",
		"textContent": ""
	},
	{
		"title": "耶稣的印记 20161206",
		"path": "http://media.febcchinese.org/streaming/mw/mw161206.mp3",
		"duration": 1760,
		"size": "14.1M",
		"albumName": "旷野吗哪 2016年冬季合集",
		"id": 6216000067,
		"albumId": 6216,
		"albumtitle": "旷野吗哪 2016年冬季合集(67)",
		"textContent": ""
	},
	{
		"title": "珍珠门 20161207",
		"path": "http://media.febcchinese.org/streaming/mw/mw161207.mp3",
		"duration": 1760,
		"size": "14.1M",
		"albumName": "旷野吗哪 2016年冬季合集",
		"id": 6216000068,
		"albumId": 6216,
		"albumtitle": "旷野吗哪 2016年冬季合集(68)",
		"textContent": ""
	},
	{
		"title": "乐意付出 20161208",
		"path": "http://media.febcchinese.org/streaming/mw/mw161208.mp3",
		"duration": 1760,
		"size": "14.1M",
		"albumName": "旷野吗哪 2016年冬季合集",
		"id": 6216000069,
		"albumId": 6216,
		"albumtitle": "旷野吗哪 2016年冬季合集(69)",
		"textContent": ""
	},
	{
		"title": "殉道者 20161209",
		"path": "http://media.febcchinese.org/streaming/mw/mw161209.mp3",
		"duration": 1760,
		"size": "14.1M",
		"albumName": "旷野吗哪 2016年冬季合集",
		"id": 6216000070,
		"albumId": 6216,
		"albumtitle": "旷野吗哪 2016年冬季合集(70)",
		"textContent": ""
	},
	{
		"title": "远离恶事 20161210",
		"path": "http://media.febcchinese.org/streaming/mw/mw161210.mp3",
		"duration": 1760,
		"size": "14.1M",
		"albumName": "旷野吗哪 2016年冬季合集",
		"id": 6216000071,
		"albumId": 6216,
		"albumtitle": "旷野吗哪 2016年冬季合集(71)",
		"textContent": ""
	},
	{
		"title": "基督的风范 20161211",
		"path": "http://media.febcchinese.org/streaming/mw/mw161211.mp3",
		"duration": 1760,
		"size": "14.1M",
		"albumName": "旷野吗哪 2016年冬季合集",
		"id": 6216000072,
		"albumId": 6216,
		"albumtitle": "旷野吗哪 2016年冬季合集(72)",
		"textContent": ""
	},
	{
		"title": "神言坚定 20161212",
		"path": "http://media.febcchinese.org/streaming/mw/mw161212.mp3",
		"duration": 1760,
		"size": "14.1M",
		"albumName": "旷野吗哪 2016年冬季合集",
		"id": 6216000073,
		"albumId": 6216,
		"albumtitle": "旷野吗哪 2016年冬季合集(73)",
		"textContent": ""
	},
	{
		"title": "擒拿狐狸 20161213",
		"path": "http://media.febcchinese.org/streaming/mw/mw161213.mp3",
		"duration": 1760,
		"size": "14.1M",
		"albumName": "旷野吗哪 2016年冬季合集",
		"id": 6216000074,
		"albumId": 6216,
		"albumtitle": "旷野吗哪 2016年冬季合集(74)",
		"textContent": ""
	},
	{
		"title": "信心的支票簿 20161214",
		"path": "http://media.febcchinese.org/streaming/mw/mw161214.mp3",
		"duration": 1760,
		"size": "14.1M",
		"albumName": "旷野吗哪 2016年冬季合集",
		"id": 6216000075,
		"albumId": 6216,
		"albumtitle": "旷野吗哪 2016年冬季合集(75)",
		"textContent": ""
	},
	{
		"title": "美的根源 20161215",
		"path": "http://media.febcchinese.org/streaming/mw/mw161215.mp3",
		"duration": 1760,
		"size": "14.1M",
		"albumName": "旷野吗哪 2016年冬季合集",
		"id": 6216000076,
		"albumId": 6216,
		"albumtitle": "旷野吗哪 2016年冬季合集(76)",
		"textContent": ""
	},
	{
		"title": "我不孤单 20161216",
		"path": "http://media.febcchinese.org/streaming/mw/mw161216.mp3",
		"duration": 1760,
		"size": "14.1M",
		"albumName": "旷野吗哪 2016年冬季合集",
		"id": 6216000077,
		"albumId": 6216,
		"albumtitle": "旷野吗哪 2016年冬季合集(77)",
		"textContent": ""
	},
	{
		"title": "耶稣领我 20161217",
		"path": "http://media.febcchinese.org/streaming/mw/mw161217.mp3",
		"duration": 1760,
		"size": "14.1M",
		"albumName": "旷野吗哪 2016年冬季合集",
		"id": 6216000078,
		"albumId": 6216,
		"albumtitle": "旷野吗哪 2016年冬季合集(78)",
		"textContent": ""
	},
	{
		"title": "与主同住 20161218",
		"path": "http://media.febcchinese.org/streaming/mw/mw161218.mp3",
		"duration": 1760,
		"size": "14.1M",
		"albumName": "旷野吗哪 2016年冬季合集",
		"id": 6216000079,
		"albumId": 6216,
		"albumtitle": "旷野吗哪 2016年冬季合集(79)",
		"textContent": ""
	},
	{
		"title": "传主福音 20161219",
		"path": "http://media.febcchinese.org/streaming/mw/mw161219.mp3",
		"duration": 1760,
		"size": "14.1M",
		"albumName": "旷野吗哪 2016年冬季合集",
		"id": 6216000080,
		"albumId": 6216,
		"albumtitle": "旷野吗哪 2016年冬季合集(80)",
		"textContent": ""
	},
	{
		"title": "谨慎脚步 20161220",
		"path": "http://media.febcchinese.org/streaming/mw/mw161220.mp3",
		"duration": 1760,
		"size": "14.1M",
		"albumName": "旷野吗哪 2016年冬季合集",
		"id": 6216000081,
		"albumId": 6216,
		"albumtitle": "旷野吗哪 2016年冬季合集(81)",
		"textContent": ""
	},
	{
		"title": "未来的我 20161221",
		"path": "http://media.febcchinese.org/streaming/mw/mw161221.mp3",
		"duration": 1760,
		"size": "14.1M",
		"albumName": "旷野吗哪 2016年冬季合集",
		"id": 6216000082,
		"albumId": 6216,
		"albumtitle": "旷野吗哪 2016年冬季合集(82)",
		"textContent": ""
	},
	{
		"title": "追求和睦 20161222",
		"path": "http://media.febcchinese.org/streaming/mw/mw161222.mp3",
		"duration": 1760,
		"size": "14.1M",
		"albumName": "旷野吗哪 2016年冬季合集",
		"id": 6216000083,
		"albumId": 6216,
		"albumtitle": "旷野吗哪 2016年冬季合集(83)",
		"textContent": ""
	},
	{
		"title": "景星导引 20161223",
		"path": "http://media.febcchinese.org/streaming/mw/mw161223.mp3",
		"duration": 1760,
		"size": "14.1M",
		"albumName": "旷野吗哪 2016年冬季合集",
		"id": 6216000084,
		"albumId": 6216,
		"albumtitle": "旷野吗哪 2016年冬季合集(84)",
		"textContent": ""
	},
	{
		"title": "如果耶稣没有来 20161224",
		"path": "http://media.febcchinese.org/streaming/mw/mw161224.mp3",
		"duration": 1760,
		"size": "14.1M",
		"albumName": "旷野吗哪 2016年冬季合集",
		"id": 6216000085,
		"albumId": 6216,
		"albumtitle": "旷野吗哪 2016年冬季合集(85)",
		"textContent": ""
	},
	{
		"title": "爱在圣诞 20161225",
		"path": "http://media.febcchinese.org/streaming/mw/mw161225.mp3",
		"duration": 1760,
		"size": "14.1M",
		"albumName": "旷野吗哪 2016年冬季合集",
		"id": 6216000086,
		"albumId": 6216,
		"albumtitle": "旷野吗哪 2016年冬季合集(86)",
		"textContent": ""
	},
	{
		"title": "奇妙策士 20161226",
		"path": "http://media.febcchinese.org/streaming/mw/mw161226.mp3",
		"duration": 1760,
		"size": "14.1M",
		"albumName": "旷野吗哪 2016年冬季合集",
		"id": 6216000087,
		"albumId": 6216,
		"albumtitle": "旷野吗哪 2016年冬季合集(87)",
		"textContent": ""
	},
	{
		"title": "祂名叫耶稣 20161227",
		"path": "http://media.febcchinese.org/streaming/mw/mw161227.mp3",
		"duration": 1760,
		"size": "14.1M",
		"albumName": "旷野吗哪 2016年冬季合集",
		"id": 6216000088,
		"albumId": 6216,
		"albumtitle": "旷野吗哪 2016年冬季合集(88)",
		"textContent": ""
	},
	{
		"title": "名录生命册 20161228",
		"path": "http://media.febcchinese.org/streaming/mw/mw161228.mp3",
		"duration": 1760,
		"size": "14.1M",
		"albumName": "旷野吗哪 2016年冬季合集",
		"id": 6216000089,
		"albumId": 6216,
		"albumtitle": "旷野吗哪 2016年冬季合集(89)",
		"textContent": ""
	},
	{
		"title": "加倍的感动 20161229",
		"path": "http://media.febcchinese.org/streaming/mw/mw161229.mp3",
		"duration": 1760,
		"size": "14.1M",
		"albumName": "旷野吗哪 2016年冬季合集",
		"id": 6216000090,
		"albumId": 6216,
		"albumtitle": "旷野吗哪 2016年冬季合集(90)",
		"textContent": ""
	},
	{
		"title": "向高处行 20161230",
		"path": "http://media.febcchinese.org/streaming/mw/mw161230.mp3",
		"duration": 1760,
		"size": "14.1M",
		"albumName": "旷野吗哪 2016年冬季合集",
		"id": 6216000091,
		"albumId": 6216,
		"albumtitle": "旷野吗哪 2016年冬季合集(91)",
		"textContent": ""
	},
	{
		"title": "绝不退后 20161231",
		"path": "http://media.febcchinese.org/streaming/mw/mw161231.mp3",
		"duration": 1760,
		"size": "14.1M",
		"albumName": "旷野吗哪 2016年冬季合集",
		"id": 6216000092,
		"albumId": 6216,
		"albumtitle": "旷野吗哪 2016年冬季合集(92)",
		"textContent": ""
	}
]